gash_client/__about__.py
gash_client/__init__.py
gash_client/config.py
gash_client/core/__init__.py
gash_client/core/base/__init__.py
gash_client/core/base/dto.py
gash_client/core/client.py
gash_client/core/permit/__init__.py
gash_client/core/permit/dto.py
gash_client/core/resource/__init__.py
gash_client/core/resource/dto.py
gash_client/core/scope/__init__.py
gash_client/core/scope/dto.py
gash_client/core/user/__init__.py
gash_client/core/user/dto.py
gash_client-0.1.1.dist-info/LICENSE
gash_client-0.1.1.dist-info/METADATA
gash_client-0.1.1.dist-info/WHEEL
gash_client-0.1.1.dist-info/RECORD
