Metadata-Version: 2.1
Name: gash-client
Version: 0.1.1
Summary: Client library for GraphDB Access Security Hub
Home-page: https://github.com/gooddelo/gash
License: MIT
Keywords: python,rabbitmq,faststream,gash,pydantic
Author: Gooddelo
Author-email: ivan@gooddelo.com
Maintainer: Max
Maintainer-email: SDback@gooddelo.com
Requires-Python: >=3.12,<4.0
Classifier: License :: OSI Approved :: MIT License
Classifier: Programming Language :: Python :: 3
Requires-Dist: faststream[rabbit] (>=0.4.5,<0.5.0)
Project-URL: Documentation, https://github.com/gooddelo/gash#readme
Project-URL: Repository, https://github.com/gooddelo/gash
